palkia/__init__.py
palkia/const/__init__.py
palkia/const/column_name.py
palkia/const/parameter.py
palkia/const/path.py
palkia/positioning/__init__.py
palkia/positioning/correction/__init__.py
palkia/positioning/correction/ble_correction.py
palkia/positioning/correction/drift.py
palkia/positioning/correction/map_matching.py
palkia/positioning/correction/stable_walking.py
palkia/positioning/correction/trajectory_corrector.py
palkia/positioning/pdr/__init__.py
palkia/positioning/pdr/filters/__init__.py
palkia/positioning/pdr/filters/base_filter.py
palkia/positioning/pdr/filters/simple_filter.py
palkia/positioning/pdr/orientation_estimator.py
palkia/positioning/pdr/pdr_estimator.py
palkia/positioning/pdr/step_estimator.py
palkia/positioning/pdr/three_dimensional_estimator.py
palkia/positioning/pdr/trajectory_calculator.py
palkia/utils/__init__.py
palkia/utils/barometer_utils.py
palkia/utils/data_loader.py
palkia/utils/data_preprocessor.py
palkia/utils/floor_map.py
palkia/utils/visualizer.py
palkia-0.2.4.dist-info/LICENSE
palkia-0.2.4.dist-info/METADATA
palkia-0.2.4.dist-info/WHEEL
palkia-0.2.4.dist-info/RECORD
